loopy/__init__.py
loopy/__main__.py
loopy/auto_test.py
loopy/check.py
loopy/cli.py
loopy/diagnostic.py
loopy/expression.py
loopy/ipython_ext.py
loopy/isl_helpers.py
loopy/loop.py
loopy/match.py
loopy/options.py
loopy/preprocess.py
loopy/py.typed
loopy/statistics.py
loopy/symbolic.py
loopy/tools.py
loopy/translation_unit.py
loopy/type_inference.py
loopy/types.py
loopy/typing.py
loopy/version.py
loopy/codegen/__init__.py
loopy/codegen/bounds.py
loopy/codegen/control.py
loopy/codegen/instruction.py
loopy/codegen/loop.py
loopy/codegen/result.py
loopy/codegen/tools.py
loopy/frontend/__init__.py
loopy/frontend/fortran/__init__.py
loopy/frontend/fortran/diagnostic.py
loopy/frontend/fortran/expression.py
loopy/frontend/fortran/translator.py
loopy/frontend/fortran/tree.py
loopy/kernel/__init__.py
loopy/kernel/array.py
loopy/kernel/creation.py
loopy/kernel/data.py
loopy/kernel/function_interface.py
loopy/kernel/instruction.py
loopy/kernel/tools.py
loopy/library/__init__.py
loopy/library/function.py
loopy/library/random123.py
loopy/library/reduction.py
loopy/schedule/__init__.py
loopy/schedule/device_mapping.py
loopy/schedule/tools.py
loopy/schedule/tree.py
loopy/target/__init__.py
loopy/target/cuda.py
loopy/target/execution.py
loopy/target/ispc.py
loopy/target/opencl.py
loopy/target/pyopencl.py
loopy/target/pyopencl_execution.py
loopy/target/python.py
loopy/target/c/__init__.py
loopy/target/c/c_execution.py
loopy/target/c/codegen/__init__.py
loopy/target/c/codegen/expression.py
loopy/target/c/compyte/.gitignore
loopy/target/c/compyte/__init__.py
loopy/target/c/compyte/array.py
loopy/target/c/compyte/dtypes.py
loopy/target/c/compyte/pyproject.toml
loopy/target/c/compyte/.github/workflows/autopush.yml
loopy/target/c/compyte/.github/workflows/ci.yml
loopy/transform/__init__.py
loopy/transform/add_barrier.py
loopy/transform/arithmetic.py
loopy/transform/array_buffer_map.py
loopy/transform/batch.py
loopy/transform/buffer.py
loopy/transform/callable.py
loopy-2025.1.dist-info/METADATA
loopy-2025.1.dist-info/WHEEL
loopy-2025.1.dist-info/licenses/LICENSE
loopy-2025.1.dist-info/RECORD
