Metadata-Version: 2.4
Name: loopy
Version: 2025.1
Summary: A code generator for array-based code on CPUs and GPUs
Project-URL: Documentation, https://documen.tician.de/loopy
Project-URL: Homepage, https://github.com/inducer/loopy
Author-email: Andreas Kloeckner <inform@tiker.net>
License: MIT
License-File: LICENSE
Classifier: Development Status :: 4 - Beta
Classifier: Intended Audience :: Developers
Classifier: Intended Audience :: Other Audience
Classifier: Intended Audience :: Science/Research
Classifier: License :: OSI Approved :: MIT License
Classifier: Natural Language :: English
Classifier: Programming Language :: Python
Classifier: Programming Language :: Python :: 3
Classifier: Topic :: Scientific/Engineering
Classifier: Topic :: Scientific/Engineering :: Information Analysis
Classifier: Topic :: Scientific/Engineering :: Mathematics
Classifier: Topic :: Scientific/Engineering :: Visualization
Classifier: Topic :: Software Development :: Libraries
Classifier: Topic :: Utilities
Requires-Python: >=3.10
Requires-Dist: cgen>=2016.1
Requires-Dist: codepy>=2017.1
Requires-Dist: colorama
Requires-Dist: constantdict
Requires-Dist: genpy>=2016.1.2
Requires-Dist: islpy>=2019.1
Requires-Dist: mako
Requires-Dist: numpy>=1.19
Requires-Dist: pymbolic>=2024.2.2
Requires-Dist: pytools>=2024.1.5
Requires-Dist: typing-extensions>=4
Provides-Extra: fortran
Requires-Dist: fparser>=0.2.0; extra == 'fortran'
Requires-Dist: ply>=3.6; extra == 'fortran'
Provides-Extra: pyopencl
Requires-Dist: pyopencl>=2022.3; extra == 'pyopencl'
